README.md
pyproject.toml
setup.py
carcharodon/__init__.py
carcharodon/bbs.py
carcharodon/kosti.py
carcharodon.egg-info/PKG-INFO
carcharodon.egg-info/SOURCES.txt
carcharodon.egg-info/dependency_links.txt
carcharodon.egg-info/entry_points.txt
carcharodon.egg-info/top_level.txt